Ernestas_data_crawler/Ernestas_data_crawler.py
Ernestas_data_crawler/Ernestas_data_crawler.pyproj
ernestas_data_crawler-0.1.0.dist-info/METADATA
ernestas_data_crawler-0.1.0.dist-info/WHEEL
ernestas_data_crawler-0.1.0.dist-info/RECORD
